cz_ossfs/__init__.py
cz_ossfs/async_oss.py
cz_ossfs/base.py
cz_ossfs/core.py
cz_ossfs/exceptions.py
cz_ossfs/file.py
cz_ossfs/utils.py
cz_ossfs-0.0.2.dist-info/LICENSE
cz_ossfs-0.0.2.dist-info/METADATA
cz_ossfs-0.0.2.dist-info/WHEEL
cz_ossfs-0.0.2.dist-info/top_level.txt
cz_ossfs-0.0.2.dist-info/RECORD
