Metadata-Version: 2.1
Name: cz-ossfs
Version: 0.0.2
Summary: fsspec filesystem for OSS
Home-page: 
Download-URL: 
Maintainer-email: 
License: Apache-2.0
Platform: any
Classifier: Programming Language :: Python :: 3
Classifier: Programming Language :: Python :: 3.8
Classifier: Programming Language :: Python :: 3.9
Classifier: Programming Language :: Python :: 3.10
Classifier: Programming Language :: Python :: 3.11
Classifier: Development Status :: 4 - Beta
Requires-Python: >=3.8
License-File: LICENSE
Requires-Dist: fsspec (==2023.5.0)
Requires-Dist: oss2 (==2.17.0)
Requires-Dist: aiooss2 (==0.2.5)
Provides-Extra: dev
Requires-Dist: pytest (==7.2.0) ; extra == 'dev'
Requires-Dist: pytest-sugar (==0.9.5) ; extra == 'dev'
Requires-Dist: pytest-cov (==3.0.0) ; extra == 'dev'
Requires-Dist: pytest-mock (==3.8.2) ; extra == 'dev'
Requires-Dist: pylint (==2.15.0) ; extra == 'dev'
Requires-Dist: pylint-pytest (==1.1.2) ; extra == 'dev'
Requires-Dist: mypy (==0.971) ; extra == 'dev'
Requires-Dist: requests (==2.31.0) ; extra == 'dev'
Requires-Dist: aliyun-python-sdk-sts (==3.1.1) ; extra == 'dev'
Requires-Dist: mkdocs (==1.3.1) ; extra == 'dev'
Requires-Dist: mkdocs-gen-files (==0.3.5) ; extra == 'dev'
Requires-Dist: mkdocs-material (==8.4.1) ; extra == 'dev'
Requires-Dist: mkdocs-section-index (==0.3.4) ; extra == 'dev'
Requires-Dist: mkdocstrings-python (==0.7.1) ; extra == 'dev'
Provides-Extra: docs
Requires-Dist: mkdocs (==1.3.1) ; extra == 'docs'
Requires-Dist: mkdocs-gen-files (==0.3.5) ; extra == 'docs'
Requires-Dist: mkdocs-material (==8.4.1) ; extra == 'docs'
Requires-Dist: mkdocs-section-index (==0.3.4) ; extra == 'docs'
Requires-Dist: mkdocstrings-python (==0.7.1) ; extra == 'docs'
Provides-Extra: tests
Requires-Dist: pytest (==7.2.0) ; extra == 'tests'
Requires-Dist: pytest-sugar (==0.9.5) ; extra == 'tests'
Requires-Dist: pytest-cov (==3.0.0) ; extra == 'tests'
Requires-Dist: pytest-mock (==3.8.2) ; extra == 'tests'
Requires-Dist: pylint (==2.15.0) ; extra == 'tests'
Requires-Dist: pylint-pytest (==1.1.2) ; extra == 'tests'
Requires-Dist: mypy (==0.971) ; extra == 'tests'
Requires-Dist: requests (==2.31.0) ; extra == 'tests'
Requires-Dist: aliyun-python-sdk-sts (==3.1.1) ; extra == 'tests'
